gcasc/__init__.py
gcasc/base.py
gcasc/config.py
gcasc/license.py
gcasc/settings.py
gcasc/utils/__init__.py
gcasc/utils/logger.py
gcasc/utils/os.py
gcasc/utils/strings.py
gcasc/utils/validators.py
gcasc/utils/yaml_env.py
gcasc/utils/yaml_include.py
tests/__init__.py
tests/config_test.py
tests/gcasc_test.py
tests/helpers.py
tests/license_test.py
tests/settings_test.py
tests/validators_test.py
tests/yaml_env_test.py
tests/yaml_include_test.py
gitlab_configuration_as_code-0.1b2.dist-info/LICENSE
gitlab_configuration_as_code-0.1b2.dist-info/METADATA
gitlab_configuration_as_code-0.1b2.dist-info/WHEEL
gitlab_configuration_as_code-0.1b2.dist-info/entry_points.txt
gitlab_configuration_as_code-0.1b2.dist-info/top_level.txt
gitlab_configuration_as_code-0.1b2.dist-info/RECORD
