Metadata-Version: 2.1
Name: gitlab-configuration-as-code
Version: 0.1b2
Summary: Manage GitLab configuration as code
Home-page: https://github.com/Roche/gitlab-configuration-as-code
Author: Mateusz Filipowicz
Author-email: mateusz.filipowicz@roche.com
License: Apache-2.0
Keywords: gitlab,configuration-as-code
Platform: UNKNOWN
Classifier: Development Status :: 4 - Beta
Classifier: Environment :: Console
Classifier: Intended Audience :: System Administrators
Classifier: License :: OSI Approved :: Apache Software License
Classifier: Natural Language :: English
Classifier: Operating System :: POSIX
Classifier: Operating System :: Microsoft :: Windows
Classifier: Programming Language :: Python
Classifier: Programming Language :: Python :: 3
Classifier: Programming Language :: Python :: 3.4
Classifier: Programming Language :: Python :: 3.5
Classifier: Programming Language :: Python :: 3.6
Classifier: Programming Language :: Python :: 3.7
Classifier: Programming Language :: Python :: 3.8
Requires-Dist: python-gitlab (>=1.13.0)
Requires-Dist: PyYAML (>=5.1.2)
